statspai/__init__.py
statspai/causal/__init__.py
statspai/causal/causal_forest.py
statspai/core/__init__.py
statspai/core/base.py
statspai/core/results.py
statspai/core/utils.py
statspai/output/__init__.py
statspai/output/outreg2.py
statspai/regression/__init__.py
statspai/regression/ols.py
statspai-0.1.0.dist-info/licenses/LICENSE
statspai-0.1.0.dist-info/METADATA
statspai-0.1.0.dist-info/WHEEL
statspai-0.1.0.dist-info/top_level.txt
statspai-0.1.0.dist-info/RECORD
