Metadata-Version: 2.4
Name: StatsPAI
Version: 0.1.0
Summary: The AI-powered Statistics & Econometrics Toolkit for Python
Author-email: Bryce Wang <bryce.wang@example.com>
Maintainer-email: Bryce Wang <bryce.wang@example.com>
License-Expression: MIT
Project-URL: Homepage, https://github.com/brycewang-stanford/pyEconometrics
Project-URL: Documentation, https://statspai.readthedocs.io/
Project-URL: Repository, https://github.com/brycewang-stanford/pyEconometrics
Project-URL: Bug Reports, https://github.com/brycewang-stanford/pyEconometrics/issues
Keywords: econometrics,statistics,regression,causal-inference,causal-forest,panel-data,instrumental-variables,stata,R,machine-learning
Classifier: Development Status :: 3 - Alpha
Classifier: Intended Audience :: Science/Research
Classifier: Operating System :: OS Independent
Classifier: Programming Language :: Python :: 3
Classifier: Programming Language :: Python :: 3.8
Classifier: Programming Language :: Python :: 3.9
Classifier: Programming Language :: Python :: 3.10
Classifier: Programming Language :: Python :: 3.11
Classifier: Programming Language :: Python :: 3.12
Classifier: Topic :: Scientific/Engineering :: Mathematics
Classifier: Topic :: Office/Business :: Financial
Requires-Python: >=3.8
License-File: LICENSE
Requires-Dist: numpy>=1.20.0
Requires-Dist: pandas>=1.3.0
Requires-Dist: scipy>=1.7.0
Requires-Dist: statsmodels>=0.13.0
Requires-Dist: linearmodels>=4.25
Requires-Dist: numba>=0.56.0
Requires-Dist: scikit-learn>=1.0.0
Requires-Dist: patsy>=0.5.0
Requires-Dist: openpyxl>=3.0.0
Requires-Dist: xlsxwriter>=3.0.0
Provides-Extra: dev
Requires-Dist: pytest>=6.0; extra == "dev"
Requires-Dist: pytest-cov; extra == "dev"
Requires-Dist: black; extra == "dev"
Requires-Dist: flake8; extra == "dev"
Requires-Dist: mypy; extra == "dev"
Requires-Dist: sphinx; extra == "dev"
Requires-Dist: sphinx-rtd-theme; extra == "dev"
Provides-Extra: performance
Requires-Dist: jax[cpu]>=0.4.0; extra == "performance"
Requires-Dist: jaxlib>=0.4.0; extra == "performance"
Provides-Extra: plotting
Requires-Dist: matplotlib>=3.5.0; extra == "plotting"
Requires-Dist: seaborn>=0.11.0; extra == "plotting"
Requires-Dist: plotly>=5.0.0; extra == "plotting"
Dynamic: license-file
